Workbook

Sheet Cost Model
A1: PaySecure Multi-Region DR Cost Model
A3: Key Assumptions
A4: Planning month hours | B4: 730 | C4: hours/month
A5: USD to INR planning FX | B5: 85 | C5: editable planning assumption
A6: Current annual infrastructure spend | B6: 80000000 | C6: INR/year; project brief
A7: Current trailing downtime | B7: 7 | C7: hours/year; project brief
A8: Revenue loss | B8: 3750000 | C8: INR/hour; project brief
A9: Merchant/SLA cost allowance | B9: 0 | C9: editable
A10: Regulatory fine allowance | B10: 0 | C10: editable
A11: Recovery labor allowance | B11: 1500000 | C11: editable planning assumption
A14: DR Tier Assumptions
A15: Tier | B15: RTO (hours) | C15: RPO (hours) | D15: DR capacity factor | E15: Notes
A16: Cold | B16: 4 | C16: 1 | D16: 0.1 | E16: Backup/restore oriented; minimal standby capacity
A17: Warm | B17: 0.5 | C17: 0.0833 | D17: 0.35 | E17: Scaled standby capacity with asynchronous replication
A18: Hot | B18: 0.1667 | C18: 0.0167 | D18: 0.7 | E18: Near-production standby; rapid promotion
A19: Active-Active | B19: 0.0167 | C19: 0.001 | D19: 1 | E19: Full multi-region serving and replication
A22: Line-Item Cost Model
A23: AWS Service Category | B23: Baseline Qty | C23: Unit | D23: Planning Rate (USD) | E23: Pricing Basis | F23: Cold Qty Factor | G23: Warm Qty Factor | H23: Hot Qty Factor | I23: Active-Active Qty Factor | J23: Cold Monthly USD | K23: Warm Monthly USD | L23: Hot Monthly USD | M23: Active-Active Monthly USD
A24: Amazon EKS | B24: 1 | C24: cluster | D24: 0.1 | E24: cluster-hour | F24: 0.1 | G24: 0.35 | H24: 0.7 | I24: 1 | J24: =B24*D24*F24 | K24: =B24*D24*G24 | L24: =B24*D24*H24 | M24: =B24*D24*I24
A25: EC2 worker nodes | B25: 24 | C25: nodes | D25: 0.404 | E25: node-hour planning | F25: 0.1 | G25: 0.35 | H25: 0.7 | I25: 1 | J25: =B25*D25*F25 | K25: =B25*D25*G25 | L25: =B25*D25*H25 | M25: =B25*D25*I25
A26: EBS | B26: 24 | C26: node volumes | D26: 35 | E26: monthly/node planning | F26: 0.1 | G26: 0.35 | H26: 0.7 | I26: 1 | J26: =B26*D26*F26 | K26: =B26*D26*G26 | L26: =B26*D26*H26 | M26: =B26*D26*I26
A27: Application Load Balancer | B27: 3 | C27: ALB | D27: 25 | E27: monthly/ALB planning | F27: 0.33 | G27: 0.5 | H27: 0.75 | I27: 1 | J27: =B27*D27*F27 | K27: =B27*D27*G27 | L27: =B27*D27*H27 | M27: =B27*D27*I27
A28: AWS WAF | B28: 1 | C28: web ACL | D28: 10 | E28: monthly planning | F28: 0.5 | G28: 0.75 | H28: 1 | I28: 1 | J28: =B28*D28*F28 | K28: =B28*D28*G28 | L28: =B28*D28*H28 | M28: =B28*D28*I28
A29: Aurora PostgreSQL | B29: 1 | C29: writer cluster | D29: 862 | E29: monthly instance planning | F29: 0.1 | G29: 0.35 | H29: 0.7 | I29: 1 | J29: =B29*D29*F29 | K29: =B29*D29*G29 | L29: =B29*D29*H29 | M29: =B29*D29*I29
A30: DynamoDB | B30: 1 | C30: regional table set | D30: 500 | E30: monthly capacity planning | F30: 0.1 | G30: 0.35 | H30: 0.7 | I30: 1 | J30: =B30*D30*F30 | K30: =B30*D30*G30 | L30: =B30*D30*H30 | M30: =B30*D30*I30
A31: ElastiCache Redis | B31: 1 | C31: cluster | D31: 500 | E31: monthly cluster planning | F31: 0.1 | G31: 0.35 | H31: 0.7 | I31: 1 | J31: =B31*D31*F31 | K31: =B31*D31*G31 | L31: =B31*D31*H31 | M31: =B31*D31*I31
A32: Amazon MSK | B32: 6 | C32: brokers | D32: 0.21 | E32: broker-hour planning | F32: 0.1 | G32: 0.35 | H32: 0.7 | I32: 1 | J32: =B32*D32*F32 | K32: =B32*D32*G32 | L32: =B32*D32*H32 | M32: =B32*D32*I32
A33: Amazon S3 | B33: 1 | C33: bucket set | D33: 100 | E33: monthly storage/requests planning | F33: 0.1 | G33: 0.35 | H33: 0.7 | I33: 1 | J33: =B33*D33*F33 | K33: =B33*D33*G33 | L33: =B33*D33*H33 | M33: =B33*D33*I33
A34: AWS KMS | B34: 10 | C34: CMKs | D34: 1 | E34: key-month | F34: 0.5 | G34: 0.75 | H34: 1 | I34: 1 | J34: =B34*D34*F34 | K34: =B34*D34*G34 | L34: =B34*D34*H34 | M34: =B34*D34*I34
A35: AWS Secrets Manager | B35: 50 | C35: secrets | D35: 0.4 | E35: secret-month planning | F35: 0.5 | G35: 0.75 | H35: 1 | I35: 1 | J35: =B35*D35*F35 | K35: =B35*D35*G35 | L35: =B35*D35*H35 | M35: =B35*D35*I35
... A42: Backup / snapshots | B42: 1 | C42: backup set | D42: 300 | E42: monthly planning | F42: 1 | G42: 0.75 | H42: 0.75 | I42: 1 | J42: =B42*D42*F42 | K42: =B42*D42*G42 | L42: =B42*D42*H42 | M42: =B42*D42*I42
A43: TOTAL MONTHLY USD | J43: =SUM(J24:J42) | K43: =SUM(K24:K42) | L43: =SUM(L24:L42) | M43: =SUM(M24:M42)
A44: TOTAL ANNUAL USD | J44: =J43*$B$4 | K44: =K43*$B$4 | L44: =L43*$B$4 | M44: =M43*$B$4
A45: TOTAL ANNUAL INR | J45: =J44*$B$5 | K45: =K44*$B$5 | L45: =L44*$B$5 | M45: =M44*$B$5

Sheet ROI Analysis
A1: DR Tier ROI and Downtime Analysis
A3: Tier | B3: Annual DR Cost (INR) | C3: RTO (hours) | D3: Residual Downtime Cost (INR) | E3: Current Downtime Cost (INR) | F3: Avoided Downtime Cost (INR) | G3: Other Annual Risk Costs (INR) | H3: Net Annual Benefit (INR) | I3: Simple ROI % | J3: Payback (years) | K3: RPO (hours) | L3: Interpretation
A4: Cold | B4: ='Cost Model'!J45 | C4: 4 | D4: =C4*'Cost Model'!$B$8 | E4: ='Cost Model'!$B$7*'Cost Model'!$B$8 | F4: =MAX(0,E4-D4) | G4: ='Cost Model'!$B$9+'Cost Model'!$B$10+'Cost Model'!$B$11 | H4: =F4-B4+G4 | I4: =IF(B4=0,0,H4/B4) | J4: =IF(H4<=0,"N/A",B4/H4) | K4: 1 | L4: Backup/restore oriented; minimal standby capacity
A5: Warm | B5: ='Cost Model'!K45 | C5: 0.5 | D5: =C5*'Cost Model'!$B$8 | E5: ='Cost Model'!$B$7*'Cost Model'!$B$8 | F5: =MAX(0,E5-D5) | G5: ='Cost Model'!$B$9+'Cost Model'!$B$10+'Cost Model'!$B$11 | H5: =F5-B5+G5 | I5: =IF(B5=0,0,H5/B5) | J5: =IF(H5<=0,"N/A",B5/H5) | K5: 0.0833 | L5: Scaled standby capacity with asynchronous replication
A6: Hot | B6: ='Cost Model'!L45 | C6: 0.1667 | D6: =C6*'Cost Model'!$B$8 | E6: ='Cost Model'!$B$7*'Cost Model'!$B$8 | F6: =MAX(0,E6-D6) | G6: ='Cost Model'!$B$9+'Cost Model'!$B$10+'Cost Model'!$B$11 | H6: =F6-B6+G6 | I6: =IF(B6=0,0,H6/B6) | J6: =IF(H6<=0,"N/A",B6/H6) | K6: 0.0167 | L6: Near-production standby; rapid promotion
A7: Active-Active | B7: ='Cost Model'!M45 | C7: 0.0167 | D7: =C7*'Cost Model'!$B$8 | E7: ='Cost Model'!$B$7*'Cost Model'!$B$8 | F7: =MAX(0,E7-D7) | G7: ='Cost Model'!$B$9+'Cost Model'!$B$10+'Cost Model'!$B$11 | H7: =F7-B7+G7 | I7: =IF(B7=0,0,H7/B7) | J7: =IF(H7<=0,"N/A",B7/H7) | K7: 0.001 | L7: Full multi-region serving and replication

Sheet Sensitivity
A1: Downtime Cost Sensitivity
A3: Revenue Loss / Hour (INR) | B3: Cold 4h | C3: Warm 0.5h | D3: Hot 0.167h | E3: Active-Active 0.017h | F3: Current 7h
A4: 2500000 | B4: =$A4*4 | C4: =$A4*0.5 | D4: =$A4*(10/60) | E4: =$A4*(1/60) | F4: =$A4*7
A5: 3750000 | B5: =$A5*4 | C5: =$A5*0.5 | D5: =$A5*(10/60) | E5: =$A5*(1/60) | F5: =$A5*7
A6: 5000000 | B6: =$A6*4 | C6: =$A6*0.5 | D6: =$A6*(10/60) | E6: =$A6*(1/60) | F6: =$A6*7
A7: 7500000 | B7: =$A7*4 | C7: =$A7*0.5 | D7: =$A7*(10/60) | E7: =$A7*(1/60) | F7: =$A7*7
A8: 10000000 | B8: =$A8*4 | C8: =$A8*0.5 | D8: =$A8*(10/60) | E8: =$A8*(1/60) | F8: =$A8*7

Sheet Sources & Notes
A1: Pricing Sources and Modeling Notes
A3: Project brief | B3: 15+ AWS service categories across Cold/Warm/Hot/Active-Active; calculate downtime costs and DR investment ROI. | C3: Project requirement
A4: Project brief | B4: Current annual infrastructure spend ₹8 crore; current trailing downtime 7 hours; target uptime 99.99% / 52.6 minutes maximum annual downtime. | C4: Project brief
A5: Project brief | B5: Direct revenue loss ~₹37.5 lakh/hour; recovery labor 500+ engineer-hours at ₹3,000/hour. | C5: Project brief
A6: AWS EKS Pricing | B6: Standard EKS cluster support is $0.10 per cluster-hour. | C6: https://aws.amazon.com/eks/pricing/
A7: AWS Route 53 Pricing | B7: Hosted zones, DNS queries and health checks are usage based; current offer includes up to 50 AWS-endpoint health checks free. | C7: https://aws.amazon.com/route53/pricing/
A8: AWS VPC / NAT | B8: NAT Gateway is charged per gateway-hour and per GB processed. | C8: https://docs.aws.amazon.com/vpc/latest/userguide/nat-gateway-pricing.html
A9: AWS MSK Pricing | B9: Provisioned MSK charges include broker usage and storage; other features and data transfer can add cost. | C9: https://aws.amazon.com/msk/pricing/
A10: AWS S3 Pricing | B10: S3 cost components include storage, requests/retrieval, data transfer and replication. | C10: https://aws.amazon.com/s3/pricing/
A11: AWS ElastiCache Pricing | B11: ElastiCache pricing varies by node/serverless usage, backups, data transfer and cross-region replication. | C11: https://aws.amazon.com/elasticache/pricing/
A12: Modeling note | B12: Planning rates are editable assumptions and are not claims of exact Mumbai/Hyderabad list prices. Replace with verified AWS Pricing Calculator outputs before final submission for exact-price validation. | C12: Control note
A13: Modeling note | B13: ROI is scenario-based: it compares the 7-hour trailing downtime baseline with each tier's assumed single-event RTO. It is not a probabilistic annual loss model. | C13: Control note
